{
	"data": [
		{
			"blogId": "startceo",
			"blogName": "김상훈소장의 창업통 _창업시장리포트",
			"category": "창업",
			"introduce": "▶김상훈 스타트비즈니스(startOK.co.kr) 대표 ▶1997년 회사설립후 스몰비즈니스컨설팅사 운영 ▶ 저서 '그래도 누군가는 대박가게를 만든다', '두번째잡으로 부자되기'외다수 ▶아이템선정 컨설팅, 경영자문, 상권분석, 시장조사 및 전수창업. 프랜차이즈컨설팅, 점포클리닉 ▶ 사무실:선릉역1번출구 샹제리제센터908호  ▶ 연락처 : 02-501-1116, 010-3260-4223  ▶ startceo@naver.com ▶ 1:1상담, 전화상담 가능",
			"nickName": "창업통 김상훈",
			"profileUrl": "https://blogpfthumb-phinf.pstatic.net/MjAyMDAxMjRfMjMg/MDAxNTc5ODMwNTc0NjM2.ZuzHbMw6xLMqiKNd7xrhiOSOOZUS9qCz7zrsjV2Ls3Eg.wvsvwyHrZOhIqTy8bm51S48cox2eom6cojkNO6SMdBAg.JPEG.startceo/Cap%2B2020-01-24%2B10-49-05-185.jpg?type=s1",
			"subscriberCount": 15442
		},
		{
			"blogId": "gimkong7127",
			"blogName": "분식&김밥 창업연구소",
			"category": "창업",
			"introduce": "26년 신뢰의 브랜드 김가네가 함께하는 분식&김밥 창업연구소",
			"nickName": "김가네",
			"profileUrl": "https://blogpfthumb-phinf.pstatic.net/MjAxOTExMjdfMjUy/MDAxNTc0ODM2NDI3NjQ5.I4n5Hw5BKbAGGSnsFjSHALicRqxasEJW_4kDnxmnOlsg.cRHipD50pqjFGdnhgxpIfKvkODxCGTJLLA3vfARzckEg.JPEG.gimkong7127/%25B1%25E8%25B0%25A1%25B3%25D7BI-02.jpg?type=s1",
			"subscriberCount": 3312
		},
		{
			"blogId": "oraen_o",
			"blogName": "그렇게카페가된다",
			"category": "창업",
			"introduce": "디자인이 필요한 모든 공간, 디자인 인테리어 및 시공,브랜딩 컨설팅, 무료 견적 방문 상담 문의주세요. Tel. 02-335-0929  / https://www.oraencafe.com",
			"nickName": "디자인 인테리어",
			"profileUrl": "https://blogpfthumb-phinf.pstatic.net/MjAxNzA0MjJfNiAg/MDAxNDkyODM3ODEyODQ5.QY_S9YWpRieEyiuQAiT_X0WD9ms3Lm_8lo51u0jNKX8g.atwdQpgDL6CuLxMRRBrmq7F_pXsLHm4S4DNcMOPnBaQg.PNG.oraen_o/KakaoTalk_20170422_140724806.png?type=s1",
			"subscriberCount": 3230
		},
		{
			"blogId": "rrnfrrnfl",
			"blogName": "☆레아의 이야기 바구니★",
			"category": "창업",
			"introduce": "블로그 팔  생각 전혀 \n없으니 블로그 구입이나\n임대 문의 절대\n하지마세요",
			"nickName": "레아",
			"profileUrl": "https://blogpfthumb-phinf.pstatic.net/20140507_137/rrnfrrnfl_13994689447454yOqj_JPEG/%BB%E7%C1%F8+112.jpg?type=s1",
			"subscriberCount": 1944
		},
		{
			"blogId": "koreasc8101",
			"blogName": "대한민국대표 창업컨설팅 한국창업센터",
			"category": "창업",
			"introduce": "회사소개:13년경력 2,300건 창업경험을 바탕으로 진실된 컨설팅을 해드리는 정직한 창업컨설팅회사입니다. 100%실매물 광고 또한 2012년부터 시행! 상담업무:초보창업,소자본창업,여성창업,은퇴창업,청년창업,부업창업,프랜차이즈창업,투잡창업 주력업무:특수상권,백화점,대형마트,아울렛,병원,휴게소,관공서,지하철역사등 입점, 커피,디저트,요식업 등 다양한 업종추천 ,MD, 양도양수, 업체 인큐베이팅",
			"nickName": "한국창업센터",
			"profileUrl": "https://blogpfthumb-phinf.pstatic.net/MjAxOTA1MjNfMTQ3/MDAxNTU4NTc1MjQwNDg2.1MiXQrzMSUfEqtEYVw61tOviTMOrYH972Owwegm7PNMg.m1ZboFqxEkIPHIkfexflcDaArqa8lEiQFqBVWSgsfTsg.PNG.koreasc8101/%25C7%25D1%25B1%25B9%25C3%25A2%25BE%25F7%25BC%25BE%25C5%25CD%2B%25B7%25CE%25B0%25ED.png?type=s1",
			"subscriberCount": 1558
		},
		{
			"blogId": "hanjang38",
			"blogName": "한팀장의 창업의 정석",
			"category": "창업",
			"introduce": "창업이 선택이 아닌 필수가 되는 시대입니다.\n\n경기가 안좋아서.... \n아는것이 없어서....\n창업을 망설이고 계신가요?\n\n정확한 정보는 필수!! 입니다. \n많은 경험을 토대로 길잡이가 되어드리겠습니다.\n\n010 - 7655 - 3357 (문의전화)\n카카오톡  아이디 : hmkda",
			"nickName": "한팀장",
			"profileUrl": "https://blogpfthumb-phinf.pstatic.net/20130306_280/hanjang38_1362532771365v6brN_JPEG/1.jpg?type=s1",
			"subscriberCount": 1313
		},
		{
			"blogId": "cafe_lunb",
			"blogName": "카페루앤비 공식 블로그",
			"category": "창업",
			"introduce": "이끌 娄 향기 馡\n커피의 향기를 이끌어내다.\n\n카페루앤비 공식 블로그 입니다.",
			"nickName": "카페루앤비",
			"profileUrl": "https://blogpfthumb-phinf.pstatic.net/MjAxODAxMDRfMjE0/MDAxNTE1MDU2OTk5MjM3.DlW0TydBdE1VCu7cJHsMcXLvGaojQUDfCL1YI6Ed1wkg.T8mAp3wCgghThab3IpyJYWtK_dj971XaVspCFp8eD1Ig.JPEG.cafe_lunb/%255B%25C4%25AB%25C6%25E4%25B7%25E7%25BE%25D8%25BA%25F1%255D%2B%25C7%25C1%25B7%25CE%25C7%25CA.jpg?type=s1",
			"subscriberCount": 1274
		},
		{
			"blogId": "withspoon_",
			"blogName": "모바일 아카데미",
			"category": "창업",
			"introduce": "(주)에이치엠\n모바일아카데미\n사업자 : 679-81-00391\n대표전화 : 1800-5020\ncafe.naver.com/halarm07",
			"nickName": "모아",
			"profileUrl": "https://blogpfthumb-phinf.pstatic.net/MjAxOTA2MTJfMjEg/MDAxNTYwMzI2OTA4MDg2.h72HHRbDVYVDVQM_HokpoKrCCf3F1Skcb_W5wA5Ev3Eg.VRBn6vJtEger6LK0oc7moz4AUvXB-WO6LRQjx6xSbZ8g.GIF.withspoon_/%25C4%25AB%25C6%25E4%25C7%25C1%25B7%25CE%25C7%25CA150_150_20190605.gif?type=s1",
			"subscriberCount": 1236
		},
		{
			"blogId": "write90",
			"blogName": "생 기업분석",
			"category": "창업",
			"introduce": "생 기업분석",
			"nickName": "생 기업분석",
			"profileUrl": "https://ssl.pstatic.net/static/blog/img_profile_default.png",
			"subscriberCount": 508
		},
		{
			"blogId": "gofhd054",
			"blogName": "알아두면 쓸모 있는 잡학다식 Lover ♥",
			"category": "창업",
			"introduce": "세상 만사 이것 저것 \n\n조금씩 건드려보는\n\n잡학다식 입니다~~",
			"nickName": "잡학다식",
			"profileUrl": "https://blogpfthumb-phinf.pstatic.net/MjAyMDAxMjNfMTM2/MDAxNTc5NzU4MDg1Mzcy.M-puBmblMclY_ASmiVoGGfHeiF0EWi1vP1JOO7plSbcg.lIdaoNq4ch2d1V_q4dRbWK_VKRCuyW4vZFYnWuoZQ6Ug.JPEG.gofhd054/library-1400313_1280.jpg?type=s1",
			"subscriberCount": 328
		}
	]
}